django_partisan/__init__.py
django_partisan/apps.py
django_partisan/config/__init__.py
django_partisan/config/const.py
django_partisan/config/processor_configs.py
django_partisan/exceptions.py
django_partisan/management/__init__.py
django_partisan/management/commands/__init__.py
django_partisan/management/commands/start_partisan.py
django_partisan/migrations/0001_initial.py
django_partisan/migrations/0002_auto_20200721_0300.py
django_partisan/migrations/__init__.py
django_partisan/models.py
django_partisan/processor.py
django_partisan/registry/__init__.py
django_partisan/registry/initializer.py
django_partisan/registry/registry.py
django_partisan/settings/__init__.py
django_partisan/settings/config.py
django_partisan/settings/const.py
django_partisan/settings/defaults.py
django_partisan/settings/settings_models.py
django_partisan/settings/utils.py
django_partisan/tests/__init__.py
django_partisan/tests/fixtures.py
django_partisan/tests/test_command.py
django_partisan/tests/test_configs.py
django_partisan/tests/test_exceptions.py
django_partisan/tests/test_models.py
django_partisan/tests/test_registry.py
django_partisan/tests/test_settings.py
django_partisan/tests/test_task_processor.py
django_partisan/tests/test_worker.py
django_partisan/tests/test_workers_manager.py
django_partisan/utils/__init__.py
django_partisan/utils/_macos.py
django_partisan/worker.py
django_partisan/workers_manager.py
django_partisan-1.6.1.dist-info/LICENSE
django_partisan-1.6.1.dist-info/WHEEL
django_partisan-1.6.1.dist-info/METADATA
django_partisan-1.6.1.dist-info/RECORD
