Metadata-Version: 2.1
Name: django-partisan
Version: 1.6.1
Summary: Framework to allow creating background tasks in django without MQ
Home-page: https://github.com/ilyachch/django-partisan
License: MIT
Author: Ilya Chichak
Author-email: ilyachch@gmail.com
Requires-Python: >=3.6,<4.0
Classifier: Development Status :: 4 - Beta
Classifier: Framework :: Django
Classifier: Intended Audience :: Developers
Classifier: License :: OSI Approved :: MIT License
Classifier: Operating System :: MacOS
Classifier: Operating System :: POSIX :: Linux
Classifier: Programming Language :: Python :: 3
Classifier: Programming Language :: Python :: 3 :: Only
Classifier: Programming Language :: Python :: 3.6
Classifier: Programming Language :: Python :: 3.7
Classifier: Programming Language :: Python :: 3.8
Classifier: Typing :: Typed
Requires-Dist: Django (>=1.9,<4)
Requires-Dist: psycopg2-binary (==2.8.2)
Requires-Dist: pydantic (>=1.6.1,<2.0.0)
Requires-Dist: pytz (==2019.1)
Requires-Dist: setproctitle (==1.1.10)
Requires-Dist: sqlparse (==0.3.0)
Project-URL: Repository, https://github.com/ilyachch/django-partisan
